exabgp_process/__init__.py
exabgp_process/http.py
exabgp_process/rabbit.py
exabgp_process-1.0.4.dist-info/LICENSE
exabgp_process-1.0.4.dist-info/METADATA
exabgp_process-1.0.4.dist-info/WHEEL
exabgp_process-1.0.4.dist-info/entry_points.txt
exabgp_process-1.0.4.dist-info/top_level.txt
exabgp_process-1.0.4.dist-info/RECORD
