Metadata-Version: 2.2
Name: exabgp_process
Version: 1.0.4
Summary: Process for ExaBGP, started by ExaBGP service
Author-email: Jiri Vrany <jiri.vrany@cesnet.cz>
License: MIT License
Project-URL: Homepage, https://github.com/CESNET/exabgp-process
Keywords: exabgp,networking,BGP,process
Classifier: Development Status :: 5 - Production/Stable
Classifier: Intended Audience :: Developers
Classifier: License :: OSI Approved :: MIT License
Classifier: Programming Language :: Python
Classifier: Programming Language :: Python :: 3
Classifier: Programming Language :: Python :: 3.9
Classifier: Programming Language :: Python :: 3.10
Classifier: Programming Language :: Python :: 3.11
Classifier: Programming Language :: Python :: 3.12
Classifier: Topic :: System :: Networking
Requires-Python: >=3.9
License-File: LICENSE
Requires-Dist: pika
Requires-Dist: python-dotenv
Requires-Dist: loguru
Requires-Dist: click
Requires-Dist: flask
